MANIFEST.in
README.md
setup.py
./src/analysis.c
./src/cholesky.c
./src/dpm.c
./src/gibbs.c
./src/mfm.c
./src/misc_math.c
./src/mixture.c
./src/module.c
./src/normal_wishart.c
./src/select.c
./src/type_check.c
bmcc/__init__.py
bmcc/base_result.py
bmcc/errors.py
bmcc/hierarchical.py
bmcc/least_squares.py
bmcc/mixture.py
bmcc/plot.py
bmcc/r_helpers.py
bmcc/simulate.py
bmcc.egg-info/PKG-INFO
bmcc.egg-info/SOURCES.txt
bmcc.egg-info/dependency_links.txt
bmcc.egg-info/requires.txt
bmcc.egg-info/top_level.txt
bmcc/models/__init__.py
bmcc/models/dpm.py
bmcc/models/mfm.py
bmcc/models/normal_wishart.py
include/analysis.h
include/cholesky.h
include/dpm.h
include/gibbs.h
include/mfm.h
include/misc_math.h
include/mixture.h
include/normal_wishart.h
include/select.h
include/type_check.h
src/analysis.c
src/cholesky.c
src/dpm.c
src/gibbs.c
src/mfm.c
src/misc_math.c
src/mixture.c
src/module.c
src/normal_wishart.c
src/select.c
src/type_check.c