Metadata-Version: 2.1
Name: bmcc
Version: 1.0.2
Summary: Implementation of Markov Chain Bayesian Clustering techniques, including DPM and MFM, with an abstract Mixture Model and Component Model API.
Home-page: https://github.com/thetianshuhuang/bmcc
Author: Tianshu Huang
Author-email: thetianshuhuang@gmail.com
License: UNKNOWN
Platform: UNKNOWN
Classifier: Programming Language :: Python :: 3
Classifier: License :: OSI Approved :: MIT License
Classifier: Operating System :: OS Independent
Classifier: Intended Audience :: Science/Research
Classifier: Natural Language :: English
Classifier: Topic :: Scientific/Engineering :: Mathematics
Classifier: Topic :: Scientific/Engineering :: Information Analysis
Requires-Python: >=3, <4
